htreader/__init__.py
htreader/htreader.py
htreader-1.0.0.dist-info/LICENSE
htreader-1.0.0.dist-info/METADATA
htreader-1.0.0.dist-info/WHEEL
htreader-1.0.0.dist-info/top_level.txt
htreader-1.0.0.dist-info/RECORD
