Metadata-Version: 2.1
Name: htreader
Version: 1.0.0
Summary: htreader is a file treatment
Home-page: UNKNOWN
Author: RAKOTONIAINA Harry Yves
Author-email: iharrysh.rakotoniaina@gmail.com
License: MIT License        
Platform: UNKNOWN
Classifier: Development Status :: 3 - Alpha
Classifier: Intended Audience :: Developers
Classifier: Programming Language :: Python :: 3.10
Classifier: Programming Language :: Python :: 3.11
Classifier: Topic :: Utilities
Requires-Python: >3.10, <3.11
License-File: LICENSE
